pypuq
